[
  {
    "name": "Honda 2023 Fit e\uff1aHEV\u6cb9\u96fb\u7248",
    "brand": "Honda",
    "year": "2023",
    "model": "Fit",
    "body": "\u6380\u80cc\u8eca",
    "door": "5\u9580",
    "seat": "5\u4eba\u5ea7",
    "car_length": "4045mm",
    "wheelbase": "2530mm",
    "power_type": "\u6cb9\u96fb\u6df7\u5408",
    "displacement": "1498cc"
  },
  {
    "name": "Mitsubishi 2015 Lancer iO 1.8\u8e8d\u52d5\u578b",
    "brand": "Mitsubishi",
    "year": "2015",
    "model": "Lancer iO",
    "body": "\u8f4e\u8eca",
    "door": "4\u9580",
    "seat": "5\u4eba\u5ea7",
    "car_length": "4585mm",
    "wheelbase": "2635mm",
    "power_type": "\u6c7d\u6cb9",
    "displacement": "1798cc"
  },
  {
    "name": "Ford 2020 Focus 4D EcoBoost 182\u4f5b\u5fc3\u7248",
    "brand": "Ford",
    "year": "2020",
    "model": "Focus 4D EcoBoost",
    "body": "\u8f4e\u8eca",
    "door": "4\u9580",
    "seat": "5\u4eba\u5ea7",
    "car_length": "4647mm",
    "wheelbase": "2700mm",
    "power_type": "\u6c7d\u6cb9",
    "displacement": "1497cc"
  },
  {
    "name": "Mazda 2020 CX-3 2.0\u65d7\u8266\u7fa8\u5b9a\u7248",
    "brand": "Mazda",
    "year": "2020",
    "model": "CX-3",
    "body": "\u6380\u80cc\u8eca,\u8de8\u754c\u4f11\u65c5\u8eca",
    "door": "5\u9580",
    "seat": "5\u4eba\u5ea7",
    "car_length": "4275mm",
    "wheelbase": "2570mm",
    "power_type": "\u6c7d\u6cb9",
    "displacement": "1998cc"
  },
  {
    "name": "Nissan 2016 Tiida 5D \u8c6a\u83ef\u5f71\u97f3\u7248",
    "brand": "Nissan",
    "year": "2016",
    "model": "Tiida 5D",
    "body": "\u6380\u80cc\u8eca",
    "door": "5\u9580",
    "seat": "5\u4eba\u5ea7",
    "car_length": "4295mm",
    "wheelbase": "2700mm",
    "power_type": "\u6c7d\u6cb9",
    "displacement": "1598cc"
  },
  {
    "name": "Subaru 2023 Crosstrek 2.0 i-S  EyeSight",
    "brand": "Subaru",
    "year": "2023",
    "model": "Crosstrek 2.0 i-S ",
    "body": "\u6380\u80cc\u8eca,\u8de8\u754c\u4f11\u65c5\u8eca",
    "door": "5\u9580",
    "seat": "5\u4eba\u5ea7",
    "car_length": "4480mm",
    "wheelbase": "2670mm",
    "power_type": "\u6c7d\u6cb9",
    "displacement": "1995cc"
  },
  {
    "name": "Honda 2009 Civic 1.8 VTi-S",
    "brand": "Honda",
    "year": "2009",
    "model": "Civic 1.8",
    "body": "\u8f4e\u8eca",
    "door": "4\u9580",
    "seat": "5\u4eba\u5ea7",
    "car_length": "4540mm",
    "wheelbase": "2700mm",
    "power_type": "\u6c7d\u6cb9",
    "displacement": "1799cc"
  },
  {
    "name": "Volvo 2014 V40 T4\u65d7\u8266\u7248",
    "brand": "Volvo",
    "year": "2014",
    "model": "V40",
    "body": "\u6380\u80cc\u8eca",
    "door": "5\u9580",
    "seat": "5\u4eba\u5ea7",
    "car_length": "4369mm",
    "wheelbase": "2647mm",
    "power_type": "\u6c7d\u6cb9",
    "displacement": "1596cc"
  },
  {
    "name": "Mazda 2018 3 4D 2.0\u65d7\u8266\u578b",
    "brand": "Mazda",
    "year": "2018",
    "model": "3 4D",
    "body": "\u8f4e\u8eca",
    "door": "4\u9580",
    "seat": "5\u4eba\u5ea7",
    "car_length": "4580mm",
    "wheelbase": "2700mm",
    "power_type": "\u6c7d\u6cb9",
    "displacement": "1998cc"
  },
  {
    "name": "Suzuki 2012 Swift 1.4 GLX",
    "brand": "Suzuki",
    "year": "2012",
    "model": "Swift 1.4",
    "body": "\u6380\u80cc\u8eca",
    "door": "5\u9580",
    "seat": "5\u4eba\u5ea7",
    "car_length": "3850mm",
    "wheelbase": "2430mm",
    "power_type": "\u6c7d\u6cb9",
    "displacement": "1372cc"
  },
  {
    "name": "Toyota 2013 Camry Hybrid-G",
    "brand": "Toyota",
    "year": "2013",
    "model": "Camry",
    "body": "\u8f4e\u8eca",
    "door": "4\u9580",
    "seat": "5\u4eba\u5ea7",
    "car_length": "4825mm",
    "wheelbase": "2775mm",
    "power_type": "\u6c7d\u6cb9",
    "displacement": "2494cc"
  },
  {
    "name": "Nissan 2023 Kicks 1.6\u65d7\u8266\u7248",
    "brand": "Nissan",
    "year": "2023",
    "model": "Kicks",
    "body": "\u6380\u80cc\u8eca,\u8de8\u754c\u4f11\u65c5\u8eca",
    "door": "5\u9580",
    "seat": "5\u4eba\u5ea7",
    "car_length": "4328mm",
    "wheelbase": "2620mm",
    "power_type": "\u6c7d\u6cb9",
    "displacement": "1598cc"
  },
  {
    "name": "Toyota 2022 Yaris 1.5 S",
    "brand": "Toyota",
    "year": "2022",
    "model": "Yaris 1.5",
    "body": "\u6380\u80cc\u8eca",
    "door": "5\u9580",
    "seat": "5\u4eba\u5ea7",
    "car_length": "4145mm",
    "wheelbase": "2550mm",
    "power_type": "\u6c7d\u6cb9",
    "displacement": "1496cc"
  },
  {
    "name": "Mitsubishi 2020 Colt Plus \u5178\u85cf\u578b",
    "brand": "Mitsubishi",
    "year": "2020",
    "model": "Colt Plus",
    "body": "\u6380\u80cc\u8eca",
    "door": "5\u9580",
    "seat": "5\u4eba\u5ea7",
    "car_length": "4320mm",
    "wheelbase": "2500mm",
    "power_type": "\u6c7d\u6cb9",
    "displacement": "1499cc"
  },
  {
    "name": "Mazda 2019 CX-3 2.0 SKY-G\u65d7\u8266\u578b",
    "brand": "Mazda",
    "year": "2019",
    "model": "CX-3 2.0",
    "body": "\u6380\u80cc\u8eca,\u8de8\u754c\u4f11\u65c5\u8eca",
    "door": "5\u9580",
    "seat": "5\u4eba\u5ea7",
    "car_length": "4275mm",
    "wheelbase": "2570mm",
    "power_type": "\u6c7d\u6cb9",
    "displacement": "1998cc"
  }
]
